lame/__init__.py
lame/hip.cpython-313-darwin.so
streamp3/__init__.py
streamp3_313compat-0.1.14.dist-info/licenses/LICENSE
streamp3_313compat-0.1.14.dist-info/METADATA
streamp3_313compat-0.1.14.dist-info/WHEEL
streamp3_313compat-0.1.14.dist-info/top_level.txt
streamp3_313compat-0.1.14.dist-info/RECORD
