Metadata-Version: 2.4
Name: streamp3-313compat
Version: 0.1.14
Summary: streaming mp3 decoder
Home-page: https://github.com/benjie-git/streamp3-313compat/
Author: Brent M. Spell
Author-email: brent@pylon.com
Classifier: Programming Language :: Python :: 3
Classifier: Operating System :: OS Independent
License-File: LICENSE
Requires-Dist: Cython
Dynamic: author
Dynamic: author-email
Dynamic: classifier
Dynamic: description
Dynamic: description-content-type
Dynamic: home-page
Dynamic: license-file
Dynamic: requires-dist
Dynamic: summary
